apolo_app_types_fixtures/__init__.py
apolo_app_types_fixtures/apolo_clients.py
apolo_app_types_fixtures/constants.py
apolo_app_types/__init__.py
apolo_app_types/app_types.py
apolo_app_types/cli.py
apolo_app_types/clients/__init__.py
apolo_app_types/clients/kube.py
apolo_app_types/dynamic_outputs/__init__.py
apolo_app_types/dynamic_outputs/filters.py
apolo_app_types/dynamic_outputs/outputs.py
apolo_app_types/dynamic_outputs/py.typed
apolo_app_types/helm/__init__.py
apolo_app_types/helm/apps/__init__.py
apolo_app_types/helm/apps/base.py
apolo_app_types/helm/apps/bundles/__init__.py
apolo_app_types/helm/apps/bundles/llm.py
apolo_app_types/helm/apps/common.py
apolo_app_types/helm/apps/custom_deployment.py
apolo_app_types/helm/apps/dockerhub.py
apolo_app_types/helm/apps/fooocus.py
apolo_app_types/helm/apps/ingress.py
apolo_app_types/helm/apps/jupyter.py
apolo_app_types/helm/apps/lightrag.py
apolo_app_types/helm/apps/llm.py
apolo_app_types/helm/apps/openwebui.py
apolo_app_types/helm/apps/privategpt.py
apolo_app_types/helm/apps/shell.py
apolo_app_types/helm/apps/spark_job.py
apolo_app_types/helm/apps/stable_diffusion.py
apolo_app_types/helm/apps/superset.py
apolo_app_types/helm/apps/text_embeddings.py
apolo_app_types/helm/apps/vscode.py
apolo_app_types/helm/apps/weaviate.py
apolo_app_types/helm/utils/__init__.py
apolo_app_types/helm/utils/buckets.py
apolo_app_types/helm/utils/credentials.py
apolo_app_types/helm/utils/database.py
apolo_app_types/helm/utils/deep_merging.py
apolo_app_types/helm/utils/dictionaries.py
apolo_app_types/helm/utils/images.py
apolo_app_types/helm/utils/pods.py
apolo_app_types/helm/utils/storage.py
apolo_app_types/helm/utils/text.py
apolo_app_types/inputs/__init__.py
apolo_app_types/inputs/args.py
apolo_app_types/job_utils.py
apolo_app_types/outputs/__init__.py
apolo_app_types/outputs/base.py
apolo_app_types/outputs/common.py
apolo_app_types/outputs/custom_deployment.py
apolo_app_types/outputs/dockerhub.py
apolo_app_types/outputs/fooocus.py
apolo_app_types-25.12.5.dist-info/METADATA
apolo_app_types-25.12.5.dist-info/WHEEL
apolo_app_types-25.12.5.dist-info/entry_points.txt
apolo_app_types-25.12.5.dist-info/RECORD
