Metadata-Version: 2.4
Name: apolo-app-types
Version: 25.12.5
Summary: Apolo Platform App Types.
License: Apache 2
Author: Apolo.us
Requires-Python: >=3.10.0,<4.0
Classifier: Development Status :: 4 - Beta
Classifier: Environment :: Console
Classifier: Intended Audience :: Developers
Classifier: Intended Audience :: Information Technology
Classifier: Intended Audience :: Science/Research
Classifier: License :: OSI Approved :: Apache Software License
Classifier: Operating System :: OS Independent
Classifier: Programming Language :: Python :: 3
Classifier: Programming Language :: Python :: 3 :: Only
Classifier: Topic :: Scientific/Engineering :: Artificial Intelligence
Classifier: Topic :: Software Development
Classifier: Topic :: Utilities
Provides-Extra: fixtures
Requires-Dist: apolo-sdk (>=25.11.1,<26.0.0)
Requires-Dist: click (>=8.0.3,<9.0.0)
Requires-Dist: httpx (>=0.28.0,<0.29.0)
Requires-Dist: jsonref (>=1.1.0,<2.0.0)
Requires-Dist: kubernetes (>=34.1.0,<35.0.0)
Requires-Dist: pydantic (>=2.12.5,<3.0.0)
Requires-Dist: pyyaml (>=6.0.3,<7.0.0)
Requires-Dist: tenacity (>=9.1.2,<10.0.0)
Requires-Dist: types-PyYAML (>=6.0.12.20250915,<7.0.0.0)
Requires-Dist: yarl (>=1.22.0,<2.0.0)
